{
  "basics": {
    "name": "Minchurl Shin (신민철)",
    "label": "Software Engineer",
    "image": "",
    "email": "minchurl001@gmail.com",
    "phone": "(+82) 10-2760-5715",
    "url": "https://minchurl.github.io",
    "summary": "SWE Candidate",
    "location": {
      "city": "Namyangju-si",
      "countryCode": "KR",
      "region": "Gyeonggi-do"
    }
  },
  "work": [
    {
      "name": "Someple",
      "position": "Fullstack developer",
      "url": "https://www.someple.com",
      "startDate": "2024-08-01",
      "endDate": "2024-12-26",
      "summary": "Refectoring auth system and maintaining webpage and api",
      "highlights": ["Next.js", "Supabase"]
    }
  ],
  "education": [
    {
      "institution": "Korea Advanced Institution of Science and Technology (KAIST)",
      "location": "Daejeon, South Korea",
      "url": "https://www.kaist.ac.kr/",
      "area": "School of Computing",
      "studyType": "Bachelor's degree",
      "startDate": "2020-03-01",
      "endDate": ""
    }
  ],
  "awards": [
    {
      "title": "4th prize, Samsung Collegiate Programming Cup",
      "date": "2023-09-01",
      "awarder": "Samsung Electronics",
      "url": "https://www.codeground.org/scpc/commons/honer/list",
      "summary": "SCPC"
    },
    {
      "title": "5th place, 2020 ICPC Seoul Regional",
      "date": "2020-11-01",
      "awarder": "NIA",
      "url": "https://icpc.global/regionals/finder/Seoul-2021/standings",
      "summary": "ICPC"
    },
    {
      "title": "Gold Prize, 2018 Korea olympiad in Informatics",
      "date": "2018-08-01",
      "awarder": "NIA",
      "summary": "KOI"
    },
    {
      "title": "Sliver Prize (21th place), 2018 Asia-Pacific Informatics Olympiad",
      "date": "2018-05-01",
      "awarder": "Innopolis University",
      "summary": "APIO"
    }
  ],
  "skills": [
    {
      "name": "Competitive Programming",
      "level": "Master",
      "keywords": ["ICPC", "Coding Test", "Codeforces"]
    }
  ],
  "languages": [
    {
      "language": "Korean",
      "fluency": "Native speaker",
      "icon": ""
    },
    {
      "language": "English",
      "fluency": "Intermediate",
      "icon": ""
    }
  ],
  "interests": [
    {
      "name": "System Programming",
      "keywords": ["File System"]
    }
  ],
  "projects": [
    {
      "name": "2024 MadCamp Summer",
      "summary": "MadCamp",
      "highlights": ["Development", "Web", "Application"],
      "startDate": "2024-06-26",
      "endDate": "2024-08-01",
      "url": "https://www.notion.so/minchurl/Madcamp-f44e92fafc2a496e9c2a350be70c5d90?pvs=4"
    }
  ]
}
